MANIFEST.in
README.md
setup.cfg
setup.py
caesar_salad.egg-info/PKG-INFO
caesar_salad.egg-info/SOURCES.txt
caesar_salad.egg-info/dependency_links.txt
caesar_salad.egg-info/entry_points.txt
caesar_salad.egg-info/top_level.txt
caesarsalad/__init__.py
caesarsalad/__main__.py
caesarsalad/caesarsalad.py
caesarsalad/words.txt