Metadata-Version: 1.0
Name: caesar-salad
Version: 2.0.0
Summary: A command-line tool to crack ROT-n Caesar Ciphers by a brute force attack on a sample of text
Home-page: https://github.com/amithkk/caesar-salad
Author: amithkk
Author-email: amithkumaran+pypi@gmail.com
License: GNU GPL v3
Platform: UNKNOWN
